{
  "db_name": "PostgreSQL",
  "query": "insert into mdp.responses (submitted_at, survey_id, answers) values ($1, $2, $3) returning *",
  "describe": {
    "columns": [
      {
        "ordinal": 0,
        "name": "id",
        "type_info": "Int4"
      },
      {
        "ordinal": 1,
        "name": "workspace_id",
        "type_info": "Text"
      },
      {
        "ordinal": 2,
        "name": "submitted_at",
        "type_info": "Timestamptz"
      },
      {
        "ordinal": 3,
        "name": "answers",
        "type_info": "Json"
      },
      {
        "ordinal": 4,
        "name": "survey_id",
        "type_info": "Text"
      }
    ],
    "parameters": {
      "Left": [
        "Timestamptz",
        "Text",
        "Json"
      ]
    },
    "nullable": [
      false,
      false,
      true,
      true,
      false
    ]
  },
  "hash": "75f2846b0d86175ffcad5e24d638247fcd81b2595160e820c1d2ca4ecdf976eb"
}
